Dex1B/Dex1B.py
Dex1B/__init__.py
dex1b-0.0.4.dist-info/METADATA
dex1b-0.0.4.dist-info/WHEEL
dex1b-0.0.4.dist-info/licenses/LICENSE
dex1b-0.0.4.dist-info/RECORD
