Metadata-Version: 2.4
Name: Dex1B
Version: 0.0.4
Summary: MMDiT
Project-URL: Homepage, https://pypi.org/project/Dex1B/
Project-URL: Repository, https://github.com/lucidrains/Dex1B
Author-email: Phil Wang <lucidrains@gmail.com>
License: MIT License
License-File: LICENSE
Keywords: artificial intelligence,deep learning,dexterity,scaling,synthetic data
Classifier: Development Status :: 4 - Beta
Classifier: Intended Audience :: Developers
Classifier: License :: OSI Approved :: MIT License
Classifier: Programming Language :: Python :: 3.9
Classifier: Topic :: Scientific/Engineering :: Artificial Intelligence
Requires-Python: >=3.9
Requires-Dist: einops>=0.8.0
Requires-Dist: gotennet-pytorch>=0.3.1
Requires-Dist: torch>=2.0
Requires-Dist: x-mlps-pytorch
Requires-Dist: x-transformers>=2.5.3
Provides-Extra: examples
Provides-Extra: test
Requires-Dist: pytest; extra == 'test'
